saffron/__init__.py
saffron/__main__.py
saffron/fit_functions/__init__.py
saffron/fit_functions/fit_pixel.py
saffron/fit_functions/fit_raster.py
saffron/fit_models/__init__.py
saffron/fit_models/gauss.py
saffron/init_handler/__init__.py
saffron/init_handler/gen_inits.depr
saffron/init_handler/gen_inits.py
saffron/init_handler/gen_inits1.depr
saffron/line_catalog/SPICE_SpecLines.json
saffron/line_catalog/__init__.py
saffron/line_catalog/catalog.py
saffron/manager/__init__.py
saffron/manager/input_config_template.json
saffron/manager/manager.py
saffron/postprocessing/__init__.py
saffron/postprocessing/compo_reader.py
saffron/utils/__init__.py
saffron/utils/denoise.py
saffron/utils/despike.py
saffron/utils/error_finder.py
saffron/utils/lock_tools.py
saffron/utils/utils.py
saffron/visualization/__init__.py
saffron/visualization/graphs.py
saffron_spice-0.1.4.dist-info/LICENSE
saffron_spice-0.1.4.dist-info/METADATA
saffron_spice-0.1.4.dist-info/WHEEL
saffron_spice-0.1.4.dist-info/entry_points.txt
saffron_spice-0.1.4.dist-info/RECORD
