Metadata-Version: 2.1
Name: saffron-spice
Version: 0.1.4
Summary: SAFFRON: Spectral Analysis Fitting Framework, Reduction Of Noise.
Home-page: https://github.com/slimguat/SAFFRON
License: MIT
Author: Slimane MZERGUAT
Author-email: slimane.mzerguat@universite-paris-saclay.fr
Requires-Python: >=3.9.10,<4.0
Classifier: License :: OSI Approved :: MIT License
Classifier: Programming Language :: Python :: 3
Classifier: Programming Language :: Python :: 3.10
Classifier: Programming Language :: Python :: 3.11
Classifier: Programming Language :: Python :: 3.12
Requires-Dist: astropy
Requires-Dist: colorama
Requires-Dist: docutils (>=0.14,<0.21)
Requires-Dist: fiplcr
Requires-Dist: ipympl
Requires-Dist: ipyparallel
Requires-Dist: ipywidgets
Requires-Dist: matplotlib
Requires-Dist: multiprocess
Requires-Dist: ndcube
Requires-Dist: numba
Requires-Dist: numpy
Requires-Dist: opencv-python
Requires-Dist: pandas
Requires-Dist: requests
Requires-Dist: rich
Requires-Dist: roman
Requires-Dist: scipy
Requires-Dist: setuptools
Requires-Dist: sospice
Requires-Dist: sunpy
Requires-Dist: tqdm
Requires-Dist: watroo
